assets/logo.gif
assets/logo.png
relativisticpy/README.md
relativisticpy/__init__.py
relativisticpy/algebras/__init__.py
relativisticpy/algebras/dirac_braket_notation.py
relativisticpy/algebras/einstein_summation.py
relativisticpy/algebras/jacobian_matrix.py
relativisticpy/algebras/quaternions.py
relativisticpy/algebras/tensor_algebra.py
relativisticpy/diffgeom/README.md
relativisticpy/diffgeom/__init__.py
relativisticpy/diffgeom/connection.py
relativisticpy/diffgeom/coord_transformation.py
relativisticpy/diffgeom/core/__init__.py
relativisticpy/diffgeom/derivatives/__init__.py
relativisticpy/diffgeom/derivatives/covariant.py
relativisticpy/diffgeom/derivatives/directional.py
relativisticpy/diffgeom/derivatives/exterior.py
relativisticpy/diffgeom/derivatives/functional.py
relativisticpy/diffgeom/derivatives/lie.py
relativisticpy/diffgeom/derivatives/partial.py
relativisticpy/diffgeom/index_algebra.py
relativisticpy/diffgeom/manifold.py
relativisticpy/diffgeom/metric.py
relativisticpy/diffgeom/paralleltransport.py
relativisticpy/diffgeom/tensor.py
relativisticpy/diffgeom/tensors/geometric.py
relativisticpy/diffgeom/tensors/kscalar.py
relativisticpy/diffgeom/tensors/metricscalar.py
relativisticpy/diffgeom/tensors/ricci.py
relativisticpy/diffgeom/tensors/ricciscalar.py
relativisticpy/diffgeom/tensors/riemann.py
relativisticpy/diffgeom/tensors/torsion.py
relativisticpy/diffgeom/tensors/weyl.py
relativisticpy/emft/README.md
relativisticpy/emft/__init__.py
relativisticpy/emft/energy_momentum.py
relativisticpy/gr/__init__.py
relativisticpy/gr/einstein.py
relativisticpy/gr/energymomentum.py
relativisticpy/gr/predeffs/__init__.py
relativisticpy/gr/predeffs/frw.py
relativisticpy/interpreter/README.md
relativisticpy/interpreter/__init__.py
relativisticpy/interpreter/analyzers/__init__.py
relativisticpy/interpreter/analyzers/base.py
relativisticpy/interpreter/analyzers/operator_lookup_tables.py
relativisticpy/interpreter/analyzers/semantic_analyser.py
relativisticpy-1.2.9.dist-info/LICENSE
relativisticpy-1.2.9.dist-info/METADATA
relativisticpy-1.2.9.dist-info/WHEEL
relativisticpy-1.2.9.dist-info/RECORD
