Metadata-Version: 2.1
Name: relativisticpy
Version: 1.2.9
Summary: You love General Relativity? You hate tedious hand calculations? You love RelativisticPy!
Author: Ashley Cottrell
Classifier: Programming Language :: Python :: 2
Classifier: Programming Language :: Python :: 2.7
Classifier: Programming Language :: Python :: 3
Classifier: Programming Language :: Python :: 3.4
Classifier: Programming Language :: Python :: 3.5
Classifier: Programming Language :: Python :: 3.6
Classifier: Programming Language :: Python :: 3.7
Classifier: Programming Language :: Python :: 3.8
Classifier: Programming Language :: Python :: 3.9
Classifier: Programming Language :: Python :: 3.10
Classifier: Programming Language :: Python :: 3.11
Requires-Dist: pytest (==7.4.3)
Requires-Dist: sympy (>=1.12,<2.0)
